IOTAssignmentServerdorachua/GrabCar.py
IOTAssignmentServerdorachua/GrabCarV2.py
IOTAssignmentServerdorachua/MyNewCarsFeeder.py
IOTAssignmentServerdorachua/MyNewCarsFeederV2.py
IOTAssignmentServerdorachua/MySocketServer.py
IOTAssignmentServerdorachua/MySocketServerV2.py
IOTAssignmentServerdorachua/SocketFeedV2.py
IOTAssignmentServerdorachua/__init__.py
IOTAssignmentServerdorachua-0.0.57.dist-info/LICENSE
IOTAssignmentServerdorachua-0.0.57.dist-info/METADATA
IOTAssignmentServerdorachua-0.0.57.dist-info/WHEEL
IOTAssignmentServerdorachua-0.0.57.dist-info/top_level.txt
IOTAssignmentServerdorachua-0.0.57.dist-info/RECORD
